setup.py
protobufp/__init__.py
protobufp/processor.py
protobufp/read_buffer.py
protobufp/serializer.py
protobufp.egg-info/PKG-INFO
protobufp.egg-info/SOURCES.txt
protobufp.egg-info/dependency_links.txt
protobufp.egg-info/not-zip-safe
protobufp.egg-info/requires.txt
protobufp.egg-info/top_level.txt
test/test.py
test/test_msg_pb2.py