Metadata-Version: 1.0
Name: protobufp
Version: 0.2.4
Summary: Adds the stream-processing to protobuf messages that you usually need to add yourself. 
Home-page: https://github.com/dsoprea/protobufp
Author: Dustin Oprea
Author-email: myselfasunder@gmail.com
License: GPL 2
Keywords: protobuf translator translation protocol protocols
Platform: UNKNOWN
